colorxs/__init__.py
colorxs-1.0.1.dist-info/METADATA
colorxs-1.0.1.dist-info/WHEEL
colorxs-1.0.1.dist-info/RECORD
