Metadata-Version: 2.1
Name: colorxs
Version: 1.0.1
Summary: Make your terminal output a little more colorful.
License: MIT
Author: Ethan Illingsworth
Author-email: illingsworth.ethan@gmail.com
Requires-Python: >=3.8,<4.0
Classifier: License :: OSI Approved :: MIT License
Classifier: Programming Language :: Python :: 3
Classifier: Programming Language :: Python :: 3.8
Classifier: Programming Language :: Python :: 3.9
Classifier: Programming Language :: Python :: 3.10
Classifier: Programming Language :: Python :: 3.11
Classifier: Programming Language :: Python :: 3.12
Classifier: Programming Language :: Python :: 3.13
